{"Operations":[{"fr":2,"fu":"Update","cl":"Particle Manager","du":45,"st":332171,"pC":0,"cI":0,"cB":0},{"fr":4,"fu":"Update","cl":"Particle Manager","du":72,"st":664411,"pC":0,"cI":0,"cB":0},{"fr":6,"fu":"Update","cl":"Particle Manager","du":60,"st":1000314,"pC":4,"cI":0,"cB":0},{"fr":8,"fu":"Update","cl":"Particle Manager","du":69,"st":1335513,"pC":8,"cI":0,"cB":0},{"fr":10,"fu":"Update","cl":"Particle Manager","du":79,"st":1664488,"pC":12,"cI":0,"cB":0},{"fr":12,"fu":"Update","cl":"Particle Manager","du":102,"st":1997351,"pC":16,"cI":0,"cB":0},{"fr":14,"fu":"Update","cl":"Particle Manager","du":119,"st":2337281,"pC":20,"cI":0,"cB":0},{"fr":16,"fu":"Update","cl":"Particle Manager","du":146,"st":2678826,"pC":24,"cI":0,"cB":0},{"fr":18,"fu":"Update","cl":"Particle Manager","du":169,"st":3018516,"pC":28,"cI":0,"cB":0},{"fr":20,"fu":"Update","cl":"Particle Manager","du":177,"st":3344197,"pC":32,"cI":0,"cB":0},{"fr":22,"fu":"Update","cl":"Particle Manager","du":341,"st":3688204,"pC":36,"cI":0,"cB":0},{"fr":24,"fu":"Update","cl":"Particle Manager","du":229,"st":4014009,"pC":40,"cI":0,"cB":0},{"fr":26,"fu":"Update","cl":"Particle Manager","du":262,"st":4355097,"pC":44,"cI":0,"cB":0},{"fr":28,"fu":"Update","cl":"Particle Manager","du":300,"st":4685752,"pC":48,"cI":0,"cB":0},{"fr":30,"fu":"Update","cl":"Particle Manager","du":340,"st":5015817,"pC":52,"cI":0,"cB":0},{"fr":32,"fu":"Update","cl":"Particle Manager","du":377,"st":5344056,"pC":56,"cI":0,"cB":0},{"fr":34,"fu":"Update","cl":"Particle Manager","du":416,"st":5685870,"pC":60,"cI":0,"cB":0},{"fr":36,"fu":"Update","cl":"Particle Manager","du":467,"st":6016321,"pC":64,"cI":0,"cB":0},{"fr":38,"fu":"Update","cl":"Particle Manager","du":540,"st":6357078,"pC":68,"cI":0,"cB":0},{"fr":40,"fu":"Update","cl":"Particle Manager","du":555,"st":6684330,"pC":72,"cI":0,"cB":0},{"fr":42,"fu":"Update","cl":"Particle Manager","du":635,"st":7015973,"pC":76,"cI":0,"cB":0},{"fr":44,"fu":"Update","cl":"Particle Manager","du":663,"st":7358764,"pC":80,"cI":0,"cB":0},{"fr":46,"fu":"Update","cl":"Particle Manager","du":721,"st":7687006,"pC":84,"cI":0,"cB":0},{"fr":48,"fu":"Update","cl":"Particle Manager","du":1412,"st":8015147,"pC":88,"cI":0,"cB":0},{"fr":50,"fu":"Update","cl":"Particle Manager","du":872,"st":8344531,"pC":92,"cI":0,"cB":0},{"fr":52,"fu":"Update","cl":"Particle Manager","du":912,"st":8673896,"pC":96,"cI":0,"cB":0},{"fr":54,"fu":"Update","cl":"Particle Manager","du":977,"st":9003915,"pC":100,"cI":0,"cB":0},{"fr":56,"fu":"Update","cl":"Particle Manager","du":1058,"st":9334071,"pC":104,"cI":0,"cB":0},{"fr":58,"fu":"Update","cl":"Particle Manager","du":1130,"st":9667661,"pC":108,"cI":0,"cB":0},{"fr":60,"fu":"Update","cl":"Particle Manager","du":1265,"st":9995821,"pC":112,"cI":0,"cB":0},{"fr":62,"fu":"Update","cl":"Particle Manager","du":1284,"st":10325025,"pC":116,"cI":0,"cB":0},{"fr":64,"fu":"Update","cl":"Particle Manager","du":1360,"st":10665848,"pC":120,"cI":0,"cB":0},{"fr":66,"fu":"Update","cl":"Particle Manager","du":1438,"st":11007443,"pC":124,"cI":0,"cB":0},{"fr":68,"fu":"Update","cl":"Particle Manager","du":1805,"st":11339846,"pC":128,"cI":0,"cB":0},{"fr":70,"fu":"Update","cl":"Particle Manager","du":1974,"st":11665892,"pC":132,"cI":0,"cB":0},{"fr":72,"fu":"Update","cl":"Particle Manager","du":2477,"st":12081579,"pC":136,"cI":0,"cB":0},{"fr":74,"fu":"Update","cl":"Particle Manager","du":1976,"st":12410416,"pC":140,"cI":0,"cB":0},{"fr":76,"fu":"Update","cl":"Particle Manager","du":2463,"st":12739821,"pC":144,"cI":0,"cB":0},{"fr":78,"fu":"Update","cl":"Particle Manager","du":2105,"st":13079773,"pC":148,"cI":0,"cB":0},{"fr":80,"fu":"Update","cl":"Particle Manager","du":2830,"st":13399647,"pC":152,"cI":0,"cB":0},{"fr":82,"fu":"Update","cl":"Particle Manager","du":2243,"st":13719348,"pC":156,"cI":0,"cB":0},{"fr":84,"fu":"Update","cl":"Particle Manager","du":2391,"st":14039450,"pC":160,"cI":0,"cB":0},{"fr":86,"fu":"Update","cl":"Particle Manager","du":2515,"st":14364302,"pC":164,"cI":0,"cB":0},{"fr":88,"fu":"Update","cl":"Particle Manager","du":2521,"st":14694156,"pC":168,"cI":0,"cB":0},{"fr":90,"fu":"Update","cl":"Particle Manager","du":2657,"st":15017002,"pC":172,"cI":0,"cB":0},{"fr":92,"fu":"Update","cl":"Particle Manager","du":3459,"st":15358544,"pC":176,"cI":0,"cB":0},{"fr":94,"fu":"Update","cl":"Particle Manager","du":2895,"st":15680878,"pC":180,"cI":0,"cB":0},{"fr":96,"fu":"Update","cl":"Particle Manager","du":6874,"st":16028172,"pC":184,"cI":0,"cB":0},{"fr":98,"fu":"Update","cl":"Particle Manager","du":3151,"st":16345225,"pC":188,"cI":0,"cB":0},{"fr":100,"fu":"Update","cl":"Particle Manager","du":3254,"st":16684673,"pC":192,"cI":0,"cB":0},{"fr":102,"fu":"Update","cl":"Particle Manager","du":3376,"st":17014099,"pC":196,"cI":0,"cB":0},{"fr":104,"fu":"Update","cl":"Particle Manager","du":4309,"st":17349450,"pC":200,"cI":0,"cB":0},{"fr":106,"fu":"Update","cl":"Particle Manager","du":3660,"st":17683281,"pC":204,"cI":0,"cB":0},{"fr":108,"fu":"Update","cl":"Particle Manager","du":4929,"st":18018887,"pC":208,"cI":0,"cB":0},{"fr":110,"fu":"Update","cl":"Particle Manager","du":4016,"st":18354323,"pC":212,"cI":0,"cB":0},{"fr":112,"fu":"Update","cl":"Particle Manager","du":4093,"st":18681184,"pC":216,"cI":0,"cB":0},{"fr":114,"fu":"Update","cl":"Particle Manager","du":5507,"st":19018551,"pC":220,"cI":0,"cB":0},{"fr":116,"fu":"Update","cl":"Particle Manager","du":4410,"st":19344211,"pC":224,"cI":0,"cB":0},{"fr":118,"fu":"Update","cl":"Particle Manager","du":4550,"st":19681391,"pC":228,"cI":0,"cB":0},{"fr":120,"fu":"Update","cl":"Particle Manager","du":6182,"st":20008016,"pC":232,"cI":0,"cB":0},{"fr":122,"fu":"Update","cl":"Particle Manager","du":4892,"st":20334357,"pC":236,"cI":0,"cB":0},{"fr":124,"fu":"Update","cl":"Particle Manager","du":5674,"st":20677084,"pC":240,"cI":0,"cB":0},{"fr":126,"fu":"Update","cl":"Particle Manager","du":6699,"st":21017410,"pC":244,"cI":0,"cB":0},{"fr":128,"fu":"Update","cl":"Particle Manager","du":5788,"st":21348541,"pC":248,"cI":0,"cB":4},{"fr":130,"fu":"Update","cl":"Particle Manager","du":5561,"st":21682939,"pC":252,"cI":0,"cB":8},{"fr":132,"fu":"Update","cl":"Particle Manager","du":6683,"st":22017344,"pC":256,"cI":0,"cB":12},{"fr":134,"fu":"Update","cl":"Particle Manager","du":6229,"st":22356421,"pC":260,"cI":0,"cB":16},{"fr":136,"fu":"Update","cl":"Particle Manager","du":6112,"st":22681795,"pC":264,"cI":0,"cB":20},{"fr":138,"fu":"Update","cl":"Particle Manager","du":8111,"st":23016853,"pC":268,"cI":0,"cB":24},{"fr":140,"fu":"Update","cl":"Particle Manager","du":6961,"st":23345116,"pC":272,"cI":0,"cB":28},{"fr":142,"fu":"Update","cl":"Particle Manager","du":6799,"st":23684975,"pC":276,"cI":0,"cB":32},{"fr":144,"fu":"Update","cl":"Particle Manager","du":6791,"st":24017546,"pC":280,"cI":0,"cB":36},{"fr":146,"fu":"Update","cl":"Particle Manager","du":7433,"st":24357175,"pC":284,"cI":0,"cB":40},{"fr":148,"fu":"Update","cl":"Particle Manager","du":7444,"st":24685737,"pC":288,"cI":0,"cB":44},{"fr":150,"fu":"Update","cl":"Particle Manager","du":7390,"st":25012761,"pC":292,"cI":0,"cB":48},{"fr":152,"fu":"Update","cl":"Particle Manager","du":9692,"st":25335329,"pC":296,"cI":0,"cB":52},{"fr":154,"fu":"Update","cl":"Particle Manager","du":7791,"st":25675114,"pC":300,"cI":0,"cB":56},{"fr":156,"fu":"Update","cl":"Particle Manager","du":9902,"st":26015621,"pC":304,"cI":0,"cB":60},{"fr":158,"fu":"Update","cl":"Particle Manager","du":8772,"st":26353286,"pC":308,"cI":0,"cB":64},{"fr":160,"fu":"Update","cl":"Particle Manager","du":10929,"st":26686005,"pC":312,"cI":0,"cB":68},{"fr":162,"fu":"Update","cl":"Particle Manager","du":8660,"st":27012815,"pC":316,"cI":0,"cB":72},{"fr":164,"fu":"Update","cl":"Particle Manager","du":10038,"st":27345243,"pC":320,"cI":0,"cB":76},{"fr":166,"fu":"Update","cl":"Particle Manager","du":9109,"st":27681318,"pC":324,"cI":0,"cB":80},{"fr":168,"fu":"Update","cl":"Particle Manager","du":12102,"st":28007950,"pC":328,"cI":0,"cB":84},{"fr":170,"fu":"Update","cl":"Particle Manager","du":9714,"st":28335195,"pC":332,"cI":0,"cB":88},{"fr":172,"fu":"Update","cl":"Particle Manager","du":10120,"st":28663982,"pC":336,"cI":0,"cB":92},{"fr":174,"fu":"Update","cl":"Particle Manager","du":10926,"st":28996438,"pC":340,"cI":0,"cB":96},{"fr":176,"fu":"Update","cl":"Particle Manager","du":17953,"st":29334659,"pC":344,"cI":0,"cB":100},{"fr":178,"fu":"Update","cl":"Particle Manager","du":10810,"st":29665945,"pC":348,"cI":0,"cB":104},{"fr":180,"fu":"Update","cl":"Particle Manager","du":13337,"st":30006961,"pC":352,"cI":0,"cB":108},{"fr":182,"fu":"Update","cl":"Particle Manager","du":11430,"st":30337325,"pC":356,"cI":0,"cB":112},{"fr":184,"fu":"Update","cl":"Particle Manager","du":11355,"st":30664597,"pC":360,"cI":0,"cB":116},{"fr":186,"fu":"Update","cl":"Particle Manager","du":11570,"st":30995781,"pC":364,"cI":0,"cB":120},{"fr":188,"fu":"Update","cl":"Particle Manager","du":11765,"st":31326689,"pC":368,"cI":0,"cB":124},{"fr":190,"fu":"Update","cl":"Particle Manager","du":12376,"st":31661713,"pC":372,"cI":0,"cB":128},{"fr":192,"fu":"Update","cl":"Particle Manager","du":12588,"st":31994905,"pC":376,"cI":0,"cB":132},{"fr":194,"fu":"Update","cl":"Particle Manager","du":14712,"st":32328727,"pC":380,"cI":0,"cB":136},{"fr":196,"fu":"Update","cl":"Particle Manager","du":13782,"st":32665508,"pC":384,"cI":0,"cB":140},{"fr":198,"fu":"Update","cl":"Particle Manager","du":13391,"st":33007273,"pC":388,"cI":0,"cB":144},{"fr":200,"fu":"Update","cl":"Particle Manager","du":13553,"st":33345292,"pC":392,"cI":0,"cB":148},{"fr":202,"fu":"Update","cl":"Particle Manager","du":13518,"st":33674895,"pC":396,"cI":0,"cB":152},{"fr":204,"fu":"Update","cl":"Particle Manager","du":14524,"st":34013982,"pC":400,"cI":0,"cB":156},{"fr":206,"fu":"Update","cl":"Particle Manager","du":14299,"st":34352252,"pC":404,"cI":0,"cB":160},{"fr":208,"fu":"Update","cl":"Particle Manager","du":15937,"st":34684318,"pC":408,"cI":0,"cB":164},{"fr":210,"fu":"Update","cl":"Particle Manager","du":15039,"st":35013863,"pC":412,"cI":0,"cB":168},{"fr":212,"fu":"Update","cl":"Particle Manager","du":15425,"st":35345985,"pC":416,"cI":0,"cB":172},{"fr":214,"fu":"Update","cl":"Particle Manager","du":15297,"st":35678031,"pC":420,"cI":0,"cB":176},{"fr":216,"fu":"Update","cl":"Particle Manager","du":15898,"st":36005291,"pC":424,"cI":0,"cB":180},{"fr":218,"fu":"Update","cl":"Particle Manager","du":16049,"st":36334328,"pC":428,"cI":0,"cB":184},{"fr":220,"fu":"Update","cl":"Particle Manager","du":16408,"st":36664156,"pC":432,"cI":0,"cB":188},{"fr":222,"fu":"Update","cl":"Particle Manager","du":18485,"st":36994410,"pC":436,"cI":0,"cB":192},{"fr":224,"fu":"Update","cl":"Particle Manager","du":17488,"st":37332865,"pC":440,"cI":0,"cB":196},{"fr":226,"fu":"Update","cl":"Particle Manager","du":18787,"st":37664452,"pC":444,"cI":0,"cB":200},{"fr":228,"fu":"Update","cl":"Particle Manager","du":19570,"st":37994887,"pC":448,"cI":0,"cB":204},{"fr":230,"fu":"Update","cl":"Particle Manager","du":21543,"st":38325100,"pC":452,"cI":0,"cB":208},{"fr":232,"fu":"Update","cl":"Particle Manager","du":18094,"st":38664106,"pC":456,"cI":0,"cB":212},{"fr":234,"fu":"Update","cl":"Particle Manager","du":18449,"st":38994378,"pC":460,"cI":0,"cB":216},{"fr":236,"fu":"Update","cl":"Particle Manager","du":19135,"st":39331738,"pC":464,"cI":0,"cB":220},{"fr":238,"fu":"Update","cl":"Particle Manager","du":19701,"st":39661035,"pC":468,"cI":0,"cB":224},{"fr":240,"fu":"Update","cl":"Particle Manager","du":19949,"st":39994123,"pC":472,"cI":0,"cB":228},{"fr":242,"fu":"Update","cl":"Particle Manager","du":21867,"st":40340569,"pC":476,"cI":0,"cB":232},{"fr":244,"fu":"Update","cl":"Particle Manager","du":20212,"st":40664537,"pC":480,"cI":0,"cB":236},{"fr":246,"fu":"Update","cl":"Particle Manager","du":20583,"st":41005340,"pC":484,"cI":0,"cB":240},{"fr":248,"fu":"Update","cl":"Particle Manager","du":21490,"st":41338674,"pC":488,"cI":0,"cB":244},{"fr":250,"fu":"Update","cl":"Particle Manager","du":20966,"st":41674159,"pC":492,"cI":0,"cB":248},{"fr":252,"fu":"Update","cl":"Particle Manager","du":21409,"st":42013098,"pC":496,"cI":0,"cB":252},{"fr":254,"fu":"Update","cl":"Particle Manager","du":22744,"st":42347250,"pC":500,"cI":0,"cB":256},{"fr":256,"fu":"Update","cl":"Particle Manager","du":22323,"st":42678677,"pC":504,"cI":0,"cB":260},{"fr":258,"fu":"Update","cl":"Particle Manager","du":22296,"st":43012387,"pC":508,"cI":0,"cB":264},{"fr":260,"fu":"Update","cl":"Particle Manager","du":26066,"st":43346985,"pC":512,"cI":0,"cB":268},{"fr":262,"fu":"Update","cl":"Particle Manager","du":23114,"st":43675748,"pC":516,"cI":0,"cB":272},{"fr":264,"fu":"Update","cl":"Particle Manager","du":28137,"st":44106146,"pC":520,"cI":0,"cB":276},{"fr":266,"fu":"Update","cl":"Particle Manager","du":24552,"st":44426433,"pC":524,"cI":0,"cB":280},{"fr":268,"fu":"Update","cl":"Particle Manager","du":27122,"st":44756224,"pC":528,"cI":0,"cB":284},{"fr":270,"fu":"Update","cl":"Particle Manager","du":25147,"st":45086411,"pC":532,"cI":0,"cB":288},{"fr":272,"fu":"Update","cl":"Particle Manager","du":26098,"st":45416118,"pC":536,"cI":0,"cB":292},{"fr":274,"fu":"Update","cl":"Particle Manager","du":28673,"st":45746562,"pC":540,"cI":0,"cB":296},{"fr":276,"fu":"Update","cl":"Particle Manager","du":25905,"st":46073107,"pC":544,"cI":0,"cB":300},{"fr":278,"fu":"Update","cl":"Particle Manager","du":29904,"st":46403595,"pC":548,"cI":0,"cB":304},{"fr":280,"fu":"Update","cl":"Particle Manager","du":31257,"st":46727891,"pC":552,"cI":0,"cB":308},{"fr":282,"fu":"Update","cl":"Particle Manager","du":27967,"st":47057525,"pC":556,"cI":0,"cB":312},{"fr":284,"fu":"Update","cl":"Particle Manager","du":29344,"st":47397431,"pC":560,"cI":0,"cB":316},{"fr":286,"fu":"Update","cl":"Particle Manager","du":31251,"st":47738479,"pC":564,"cI":0,"cB":320},{"fr":288,"fu":"Update","cl":"Particle Manager","du":31474,"st":48078617,"pC":568,"cI":0,"cB":324},{"fr":290,"fu":"Update","cl":"Particle Manager","du":33263,"st":48419118,"pC":572,"cI":0,"cB":328},{"fr":292,"fu":"Update","cl":"Particle Manager","du":30250,"st":48749523,"pC":576,"cI":0,"cB":332},{"fr":294,"fu":"Update","cl":"Particle Manager","du":29624,"st":49068917,"pC":580,"cI":0,"cB":336},{"fr":296,"fu":"Update","cl":"Particle Manager","du":33700,"st":49399163,"pC":584,"cI":0,"cB":340},{"fr":298,"fu":"Update","cl":"Particle Manager","du":33074,"st":49723693,"pC":588,"cI":0,"cB":344},{"fr":300,"fu":"Update","cl":"Particle Manager","du":34259,"st":50043793,"pC":592,"cI":0,"cB":348},{"fr":302,"fu":"Update","cl":"Particle Manager","du":36752,"st":50364952,"pC":596,"cI":0,"cB":352},{"fr":304,"fu":"Update","cl":"Particle Manager","du":32572,"st":50691761,"pC":600,"cI":0,"cB":356},{"fr":306,"fu":"Update","cl":"Particle Manager","du":31758,"st":51012001,"pC":604,"cI":0,"cB":360},{"fr":308,"fu":"Update","cl":"Particle Manager","du":33766,"st":51342657,"pC":608,"cI":0,"cB":364},{"fr":310,"fu":"Update","cl":"Particle Manager","du":32904,"st":51672957,"pC":612,"cI":0,"cB":368},{"fr":312,"fu":"Update","cl":"Particle Manager","du":35956,"st":52002170,"pC":616,"cI":0,"cB":372},{"fr":314,"fu":"Update","cl":"Particle Manager","du":35389,"st":52325570,"pC":620,"cI":0,"cB":376},{"fr":316,"fu":"Update","cl":"Particle Manager","du":38164,"st":52668820,"pC":624,"cI":0,"cB":380},{"fr":318,"fu":"Update","cl":"Particle Manager","du":34257,"st":53003993,"pC":628,"cI":0,"cB":384},{"fr":320,"fu":"Update","cl":"Particle Manager","du":36885,"st":53336499,"pC":632,"cI":0,"cB":388},{"fr":322,"fu":"Update","cl":"Particle Manager","du":35154,"st":53664140,"pC":636,"cI":0,"cB":392},{"fr":324,"fu":"Update","cl":"Particle Manager","du":36128,"st":54003988,"pC":640,"cI":0,"cB":396},{"fr":326,"fu":"Update","cl":"Particle Manager","du":36265,"st":54335968,"pC":644,"cI":0,"cB":400},{"fr":328,"fu":"Update","cl":"Particle Manager","du":44291,"st":54764510,"pC":648,"cI":0,"cB":404},{"fr":330,"fu":"Update","cl":"Particle Manager","du":36897,"st":55094153,"pC":652,"cI":0,"cB":408},{"fr":332,"fu":"Update","cl":"Particle Manager","du":38453,"st":55434417,"pC":656,"cI":0,"cB":412},{"fr":334,"fu":"Update","cl":"Particle Manager","du":38583,"st":55772866,"pC":660,"cI":0,"cB":416},{"fr":336,"fu":"Update","cl":"Particle Manager","du":42802,"st":56092840,"pC":664,"cI":0,"cB":420},{"fr":338,"fu":"Update","cl":"Particle Manager","du":39173,"st":56412427,"pC":668,"cI":0,"cB":424},{"fr":340,"fu":"Update","cl":"Particle Manager","du":39700,"st":56745798,"pC":672,"cI":0,"cB":428},{"fr":342,"fu":"Update","cl":"Particle Manager","du":41352,"st":57083536,"pC":676,"cI":0,"cB":432},{"fr":344,"fu":"Update","cl":"Particle Manager","du":53360,"st":57423598,"pC":680,"cI":0,"cB":436},{"fr":346,"fu":"Update","cl":"Particle Manager","du":44492,"st":57754438,"pC":684,"cI":0,"cB":440},{"fr":348,"fu":"Update","cl":"Particle Manager","du":45140,"st":58096576,"pC":688,"cI":0,"cB":444},{"fr":350,"fu":"Update","cl":"Particle Manager","du":46627,"st":58430238,"pC":692,"cI":0,"cB":448},{"fr":352,"fu":"Update","cl":"Particle Manager","du":48090,"st":58766036,"pC":696,"cI":0,"cB":452},{"fr":354,"fu":"Update","cl":"Particle Manager","du":45672,"st":59099774,"pC":700,"cI":0,"cB":456},{"fr":356,"fu":"Update","cl":"Particle Manager","du":55052,"st":59420224,"pC":704,"cI":0,"cB":460},{"fr":358,"fu":"Update","cl":"Particle Manager","du":48796,"st":59755384,"pC":708,"cI":0,"cB":468},{"fr":360,"fu":"Update","cl":"Particle Manager","du":52685,"st":60093350,"pC":712,"cI":0,"cB":476},{"fr":362,"fu":"Update","cl":"Particle Manager","du":48898,"st":60412986,"pC":716,"cI":0,"cB":484},{"fr":364,"fu":"Update","cl":"Particle Manager","du":57633,"st":60738398,"pC":720,"cI":0,"cB":492},{"fr":366,"fu":"Update","cl":"Particle Manager","du":46274,"st":61067991,"pC":724,"cI":0,"cB":500},{"fr":368,"fu":"Update","cl":"Particle Manager","du":49699,"st":61398353,"pC":728,"cI":0,"cB":508},{"fr":370,"fu":"Update","cl":"Particle Manager","du":51256,"st":61719640,"pC":732,"cI":0,"cB":516},{"fr":372,"fu":"Update","cl":"Particle Manager","du":50862,"st":62037132,"pC":736,"cI":0,"cB":524},{"fr":374,"fu":"Update","cl":"Particle Manager","du":48018,"st":62367030,"pC":740,"cI":0,"cB":532},{"fr":376,"fu":"Update","cl":"Particle Manager","du":49773,"st":62684187,"pC":744,"cI":0,"cB":540},{"fr":378,"fu":"Update","cl":"Particle Manager","du":49074,"st":63014405,"pC":748,"cI":0,"cB":548},{"fr":380,"fu":"Update","cl":"Particle Manager","du":54047,"st":63343570,"pC":752,"cI":0,"cB":556},{"fr":382,"fu":"Update","cl":"Particle Manager","du":50153,"st":63666989,"pC":756,"cI":0,"cB":564},{"fr":384,"fu":"Update","cl":"Particle Manager","du":54774,"st":64007470,"pC":760,"cI":0,"cB":572},{"fr":386,"fu":"Update","cl":"Particle Manager","du":58129,"st":64340947,"pC":764,"cI":0,"cB":580},{"fr":388,"fu":"Update","cl":"Particle Manager","du":58251,"st":64666240,"pC":768,"cI":0,"cB":588},{"fr":390,"fu":"Update","cl":"Particle Manager","du":59416,"st":65005984,"pC":772,"cI":0,"cB":596},{"fr":392,"fu":"Update","cl":"Particle Manager","du":55238,"st":65345842,"pC":776,"cI":0,"cB":604},{"fr":394,"fu":"Update","cl":"Particle Manager","du":53666,"st":65674853,"pC":780,"cI":0,"cB":612},{"fr":396,"fu":"Update","cl":"Particle Manager","du":55080,"st":66008207,"pC":784,"cI":0,"cB":620},{"fr":398,"fu":"Update","cl":"Particle Manager","du":55868,"st":66343966,"pC":788,"cI":0,"cB":628},{"fr":400,"fu":"Update","cl":"Particle Manager","du":54792,"st":66672332,"pC":792,"cI":0,"cB":636},{"fr":402,"fu":"Update","cl":"Particle Manager","du":55667,"st":66994113,"pC":796,"cI":0,"cB":644},{"fr":404,"fu":"Update","cl":"Particle Manager","du":56931,"st":67326713,"pC":800,"cI":0,"cB":652},{"fr":406,"fu":"Update","cl":"Particle Manager","du":57601,"st":67658741,"pC":804,"cI":0,"cB":660},{"fr":408,"fu":"Update","cl":"Particle Manager","du":57121,"st":67991473,"pC":808,"cI":0,"cB":668},{"fr":410,"fu":"Update","cl":"Particle Manager","du":58292,"st":68327517,"pC":812,"cI":0,"cB":676},{"fr":412,"fu":"Update","cl":"Particle Manager","du":59753,"st":68656186,"pC":816,"cI":0,"cB":684},{"fr":414,"fu":"Update","cl":"Particle Manager","du":60990,"st":68993685,"pC":820,"cI":0,"cB":692},{"fr":416,"fu":"Update","cl":"Particle Manager","du":61472,"st":69327205,"pC":824,"cI":0,"cB":700},{"fr":418,"fu":"Update","cl":"Particle Manager","du":60076,"st":69663048,"pC":828,"cI":0,"cB":708},{"fr":420,"fu":"Update","cl":"Particle Manager","du":61816,"st":69990397,"pC":832,"cI":0,"cB":716},{"fr":422,"fu":"Update","cl":"Particle Manager","du":61102,"st":70326079,"pC":836,"cI":0,"cB":724},{"fr":424,"fu":"Update","cl":"Particle Manager","du":61615,"st":70655290,"pC":840,"cI":0,"cB":732},{"fr":426,"fu":"Update","cl":"Particle Manager","du":64065,"st":70990016,"pC":844,"cI":0,"cB":740},{"fr":428,"fu":"Update","cl":"Particle Manager","du":63596,"st":71327750,"pC":848,"cI":0,"cB":748},{"fr":430,"fu":"Update","cl":"Particle Manager","du":64478,"st":71655723,"pC":852,"cI":0,"cB":756},{"fr":432,"fu":"Update","cl":"Particle Manager","du":63989,"st":71986277,"pC":856,"cI":0,"cB":764},{"fr":434,"fu":"Update","cl":"Particle Manager","du":65520,"st":72327450,"pC":860,"cI":0,"cB":772},{"fr":436,"fu":"Update","cl":"Particle Manager","du":66089,"st":72655883,"pC":864,"cI":0,"cB":780},{"fr":438,"fu":"Update","cl":"Particle Manager","du":66477,"st":72986103,"pC":868,"cI":0,"cB":788},{"fr":440,"fu":"Update","cl":"Particle Manager","du":67165,"st":73325384,"pC":872,"cI":0,"cB":796},{"fr":442,"fu":"Update","cl":"Particle Manager","du":66972,"st":73668231,"pC":876,"cI":0,"cB":804},{"fr":444,"fu":"Update","cl":"Particle Manager","du":68747,"st":73994536,"pC":880,"cI":0,"cB":812},{"fr":446,"fu":"Update","cl":"Particle Manager","du":69992,"st":74327976,"pC":884,"cI":0,"cB":820},{"fr":448,"fu":"Update","cl":"Particle Manager","du":69041,"st":74656257,"pC":888,"cI":0,"cB":828},{"fr":450,"fu":"Update","cl":"Particle Manager","du":82054,"st":74985546,"pC":892,"cI":0,"cB":836},{"fr":452,"fu":"Update","cl":"Particle Manager","du":70089,"st":75324165,"pC":896,"cI":0,"cB":844},{"fr":454,"fu":"Update","cl":"Particle Manager","du":70881,"st":75653862,"pC":900,"cI":0,"cB":852},{"fr":456,"fu":"Update","cl":"Particle Manager","du":72467,"st":75987641,"pC":904,"cI":0,"cB":860},{"fr":458,"fu":"Update","cl":"Particle Manager","du":73222,"st":76324473,"pC":908,"cI":0,"cB":868},{"fr":460,"fu":"Update","cl":"Particle Manager","du":74479,"st":76656575,"pC":912,"cI":0,"cB":876},{"fr":462,"fu":"Update","cl":"Particle Manager","du":81713,"st":76987377,"pC":916,"cI":0,"cB":884},{"fr":464,"fu":"Update","cl":"Particle Manager","du":76735,"st":77324362,"pC":920,"cI":0,"cB":892},{"fr":466,"fu":"Update","cl":"Particle Manager","du":77170,"st":77654788,"pC":924,"cI":0,"cB":900},{"fr":468,"fu":"Update","cl":"Particle Manager","du":78448,"st":77984363,"pC":928,"cI":0,"cB":908},{"fr":470,"fu":"Update","cl":"Particle Manager","du":78253,"st":78326498,"pC":932,"cI":0,"cB":916},{"fr":472,"fu":"Update","cl":"Particle Manager","du":77131,"st":78657669,"pC":936,"cI":0,"cB":924},{"fr":474,"fu":"Update","cl":"Particle Manager","du":78649,"st":78993753,"pC":940,"cI":0,"cB":932},{"fr":476,"fu":"Update","cl":"Particle Manager","du":79874,"st":79324339,"pC":944,"cI":0,"cB":940},{"fr":478,"fu":"Update","cl":"Particle Manager","du":79925,"st":79658979,"pC":948,"cI":0,"cB":948},{"fr":480,"fu":"Update","cl":"Particle Manager","du":79224,"st":79993809,"pC":952,"cI":0,"cB":956},{"fr":482,"fu":"Update","cl":"Particle Manager","du":84839,"st":80334311,"pC":956,"cI":0,"cB":964},{"fr":484,"fu":"Update","cl":"Particle Manager","du":81400,"st":80673985,"pC":960,"cI":0,"cB":972},{"fr":486,"fu":"Update","cl":"Particle Manager","du":81626,"st":81004091,"pC":964,"cI":0,"cB":980},{"fr":488,"fu":"Update","cl":"Particle Manager","du":82225,"st":81337360,"pC":968,"cI":0,"cB":988},{"fr":490,"fu":"Update","cl":"Particle Manager","du":82513,"st":81666677,"pC":972,"cI":0,"cB":996},{"fr":492,"fu":"Update","cl":"Particle Manager","du":83537,"st":81995183,"pC":976,"cI":0,"cB":1004},{"fr":494,"fu":"Update","cl":"Particle Manager","du":87073,"st":82325764,"pC":980,"cI":0,"cB":1012},{"fr":496,"fu":"Update","cl":"Particle Manager","du":85262,"st":82662787,"pC":984,"cI":0,"cB":1020},{"fr":498,"fu":"Update","cl":"Particle Manager","du":86447,"st":82996017,"pC":988,"cI":0,"cB":1028},{"fr":500,"fu":"Update","cl":"Particle Manager","du":86906,"st":83329286,"pC":992,"cI":0,"cB":1036},{"fr":502,"fu":"Update","cl":"Particle Manager","du":87255,"st":83656726,"pC":996,"cI":0,"cB":1044},{"fr":504,"fu":"Update","cl":"Particle Manager","du":99596,"st":83990698,"pC":1000,"cI":0,"cB":1052},{"fr":506,"fu":"Update","cl":"Particle Manager","du":88621,"st":84325801,"pC":1004,"cI":0,"cB":1060},{"fr":508,"fu":"Update","cl":"Particle Manager","du":96813,"st":84667433,"pC":1008,"cI":0,"cB":1068},{"fr":510,"fu":"Update","cl":"Particle Manager","du":91420,"st":85004201,"pC":1012,"cI":0,"cB":1076},{"fr":512,"fu":"Update","cl":"Particle Manager","du":90176,"st":85337403,"pC":1016,"cI":0,"cB":1084},{"fr":514,"fu":"Update","cl":"Particle Manager","du":95813,"st":85681136,"pC":1020,"cI":0,"cB":1092},{"fr":516,"fu":"Update","cl":"Particle Manager","du":97387,"st":86005092,"pC":1024,"cI":0,"cB":1100},{"fr":518,"fu":"Update","cl":"Particle Manager","du":92817,"st":86333951,"pC":1028,"cI":0,"cB":1108},{"fr":520,"fu":"Update","cl":"Particle Manager","du":94473,"st":86675263,"pC":1032,"cI":0,"cB":1116},{"fr":522,"fu":"Update","cl":"Particle Manager","du":98158,"st":87007846,"pC":1036,"cI":0,"cB":1124},{"fr":524,"fu":"Update","cl":"Particle Manager","du":94865,"st":87336878,"pC":1040,"cI":0,"cB":1132},{"fr":526,"fu":"Update","cl":"Particle Manager","du":106375,"st":87667072,"pC":1044,"cI":0,"cB":1140},{"fr":528,"fu":"Update","cl":"Particle Manager","du":99561,"st":88006396,"pC":1048,"cI":0,"cB":1148},{"fr":530,"fu":"Update","cl":"Particle Manager","du":103979,"st":88346872,"pC":1052,"cI":0,"cB":1156},{"fr":532,"fu":"Update","cl":"Particle Manager","du":97746,"st":88673439,"pC":1056,"cI":0,"cB":1164},{"fr":534,"fu":"Update","cl":"Particle Manager","du":102623,"st":89001486,"pC":1060,"cI":0,"cB":1172},{"fr":536,"fu":"Update","cl":"Particle Manager","du":105636,"st":89331366,"pC":1064,"cI":0,"cB":1180},{"fr":538,"fu":"Update","cl":"Particle Manager","du":100602,"st":89656189,"pC":1068,"cI":0,"cB":1188},{"fr":540,"fu":"Update","cl":"Particle Manager","du":100268,"st":89988900,"pC":1072,"cI":0,"cB":1196},{"fr":542,"fu":"Update","cl":"Particle Manager","du":101190,"st":90325848,"pC":1076,"cI":0,"cB":1204},{"fr":544,"fu":"Update","cl":"Particle Manager","du":103672,"st":90655317,"pC":1080,"cI":0,"cB":1212},{"fr":546,"fu":"Update","cl":"Particle Manager","du":102962,"st":90988730,"pC":1084,"cI":0,"cB":1220},{"fr":548,"fu":"Update","cl":"Particle Manager","du":114098,"st":91324302,"pC":1088,"cI":0,"cB":1228},{"fr":550,"fu":"Update","cl":"Particle Manager","du":104452,"st":91654384,"pC":1092,"cI":0,"cB":1236},{"fr":552,"fu":"Update","cl":"Particle Manager","du":109719,"st":91994398,"pC":1096,"cI":0,"cB":1244},{"fr":554,"fu":"Update","cl":"Particle Manager","du":124093,"st":92327728,"pC":1100,"cI":0,"cB":1252},{"fr":556,"fu":"Update","cl":"Particle Manager","du":107501,"st":92656855,"pC":1104,"cI":0,"cB":1260},{"fr":558,"fu":"Update","cl":"Particle Manager","du":107878,"st":92994219,"pC":1108,"cI":0,"cB":1268},{"fr":560,"fu":"Update","cl":"Particle Manager","du":116438,"st":93342532,"pC":1112,"cI":0,"cB":1276},{"fr":562,"fu":"Update","cl":"Particle Manager","du":110111,"st":93671797,"pC":1116,"cI":0,"cB":1284},{"fr":564,"fu":"Update","cl":"Particle Manager","du":110361,"st":94001682,"pC":1120,"cI":0,"cB":1292},{"fr":566,"fu":"Update","cl":"Particle Manager","du":115937,"st":94331638,"pC":1124,"cI":0,"cB":1300},{"fr":568,"fu":"Update","cl":"Particle Manager","du":114806,"st":94657068,"pC":1128,"cI":0,"cB":1308},{"fr":570,"fu":"Update","cl":"Particle Manager","du":125516,"st":94985852,"pC":1132,"cI":0,"cB":1316},{"fr":573,"fu":"Update","cl":"Particle Manager","du":113316,"st":95487143,"pC":1136,"cI":0,"cB":1324},{"fr":574,"fu":"Update","cl":"Particle Manager","du":114028,"st":95658810,"pC":1140,"cI":0,"cB":1336},{"fr":576,"fu":"Update","cl":"Particle Manager","du":114548,"st":95986385,"pC":1144,"cI":0,"cB":1348},{"fr":579,"fu":"Update","cl":"Particle Manager","du":115474,"st":96484046,"pC":1148,"cI":0,"cB":1360},{"fr":580,"fu":"Update","cl":"Particle Manager","du":117703,"st":96655446,"pC":1152,"cI":0,"cB":1372},{"fr":582,"fu":"Update","cl":"Particle Manager","du":126827,"st":97152841,"pC":1156,"cI":0,"cB":1384},{"fr":584,"fu":"Update","cl":"Particle Manager","du":201589,"st":97475468,"pC":1160,"cI":0,"cB":1396},{"fr":585,"fu":"Update","cl":"Particle Manager","du":208612,"st":97704314,"pC":1164,"cI":0,"cB":1408},{"fr":587,"fu":"Update","cl":"Particle Manager","du":158008,"st":98116563,"pC":1168,"cI":0,"cB":1420},{"fr":589,"fu":"Update","cl":"Particle Manager","du":119992,"st":98474569,"pC":1172,"cI":0,"cB":1432},{"fr":591,"fu":"Update","cl":"Particle Manager","du":124203,"st":98804984,"pC":1176,"cI":0,"cB":1444},{"fr":593,"fu":"Update","cl":"Particle Manager","du":125255,"st":99145165,"pC":1180,"cI":0,"cB":1456},{"fr":595,"fu":"Update","cl":"Particle Manager","du":123569,"st":99485506,"pC":1184,"cI":0,"cB":1468},{"fr":596,"fu":"Update","cl":"Particle Manager","du":127327,"st":99654544,"pC":1188,"cI":0,"cB":1480},{"fr":599,"fu":"Update","cl":"Particle Manager","du":128742,"st":100146317,"pC":1192,"cI":0,"cB":1492},{"fr":601,"fu":"Update","cl":"Particle Manager","du":125072,"st":100482271,"pC":1196,"cI":0,"cB":1504},{"fr":603,"fu":"Update","cl":"Particle Manager","du":129373,"st":100814228,"pC":1200,"cI":0,"cB":1516},{"fr":604,"fu":"Update","cl":"Particle Manager","du":127047,"st":100984577,"pC":1204,"cI":0,"cB":1528},{"fr":607,"fu":"Update","cl":"Particle Manager","du":137425,"st":101486492,"pC":1208,"cI":0,"cB":1540},{"fr":608,"fu":"Update","cl":"Particle Manager","du":130391,"st":101659113,"pC":1212,"cI":0,"cB":1552},{"fr":611,"fu":"Update","cl":"Particle Manager","du":144279,"st":102143890,"pC":1216,"cI":0,"cB":1564},{"fr":613,"fu":"Update","cl":"Particle Manager","du":132909,"st":102491567,"pC":1220,"cI":0,"cB":1576},{"fr":614,"fu":"Update","cl":"Particle Manager","du":131748,"st":102655451,"pC":1224,"cI":0,"cB":1588},{"fr":617,"fu":"Update","cl":"Particle Manager","du":135153,"st":103144026,"pC":1228,"cI":0,"cB":1600},{"fr":619,"fu":"Update","cl":"Particle Manager","du":147101,"st":103473116,"pC":1232,"cI":0,"cB":1612},{"fr":621,"fu":"Update","cl":"Particle Manager","du":136542,"st":103813914,"pC":1236,"cI":0,"cB":1624},{"fr":623,"fu":"Update","cl":"Particle Manager","du":137661,"st":104143655,"pC":1240,"cI":0,"cB":1636},{"fr":625,"fu":"Update","cl":"Particle Manager","du":135243,"st":104474561,"pC":1244,"cI":0,"cB":1648},{"fr":627,"fu":"Update","cl":"Particle Manager","du":136621,"st":104811248,"pC":1248,"cI":0,"cB":1660},{"fr":629,"fu":"Update","cl":"Particle Manager","du":144647,"st":105144857,"pC":1252,"cI":0,"cB":1672},{"fr":630,"fu":"Update","cl":"Particle Manager","du":137665,"st":105324187,"pC":1256,"cI":0,"cB":1684},{"fr":632,"fu":"Update","cl":"Particle Manager","du":143108,"st":105654238,"pC":1260,"cI":0,"cB":1696},{"fr":634,"fu":"Update","cl":"Particle Manager","du":143363,"st":105994916,"pC":1264,"cI":0,"cB":1708},{"fr":636,"fu":"Update","cl":"Particle Manager","du":146301,"st":106335207,"pC":1268,"cI":0,"cB":1720},{"fr":638,"fu":"Update","cl":"Particle Manager","du":144441,"st":106683442,"pC":1272,"cI":0,"cB":1732},{"fr":640,"fu":"Update","cl":"Particle Manager","du":148739,"st":107021736,"pC":1276,"cI":0,"cB":1744},{"fr":642,"fu":"Update","cl":"Particle Manager","du":163154,"st":107361312,"pC":1280,"cI":0,"cB":1756},{"fr":644,"fu":"Update","cl":"Particle Manager","du":144922,"st":107711276,"pC":1284,"cI":0,"cB":1768},{"fr":646,"fu":"Update","cl":"Particle Manager","du":146971,"st":108060935,"pC":1288,"cI":0,"cB":1780},{"fr":648,"fu":"Update","cl":"Particle Manager","du":149332,"st":108411450,"pC":1292,"cI":0,"cB":1792},{"fr":650,"fu":"Update","cl":"Particle Manager","du":150138,"st":108751048,"pC":1296,"cI":0,"cB":1804},{"fr":652,"fu":"Update","cl":"Particle Manager","du":150711,"st":109091619,"pC":1300,"cI":0,"cB":1816},{"fr":654,"fu":"Update","cl":"Particle Manager","du":152634,"st":109431700,"pC":1304,"cI":0,"cB":1828},{"fr":656,"fu":"Update","cl":"Particle Manager","du":153332,"st":109781557,"pC":1308,"cI":0,"cB":1840},{"fr":658,"fu":"Update","cl":"Particle Manager","du":162130,"st":110150858,"pC":1312,"cI":0,"cB":1852},{"fr":659,"fu":"Update","cl":"Particle Manager","du":152311,"st":110337154,"pC":1316,"cI":0,"cB":1864},{"fr":661,"fu":"Update","cl":"Particle Manager","du":157430,"st":110690453,"pC":1320,"cI":0,"cB":1876},{"fr":663,"fu":"Update","cl":"Particle Manager","du":161428,"st":111041816,"pC":1324,"cI":0,"cB":1888},{"fr":665,"fu":"Update","cl":"Particle Manager","du":168103,"st":111401902,"pC":1328,"cI":0,"cB":1900},{"fr":667,"fu":"Update","cl":"Particle Manager","du":162331,"st":111761100,"pC":1332,"cI":0,"cB":1912},{"fr":669,"fu":"Update","cl":"Particle Manager","du":160521,"st":112125255,"pC":1336,"cI":0,"cB":1924},{"fr":671,"fu":"Update","cl":"Particle Manager","du":158671,"st":112481727,"pC":1340,"cI":0,"cB":1936},{"fr":672,"fu":"Update","cl":"Particle Manager","du":157712,"st":112666638,"pC":1344,"cI":0,"cB":1948},{"fr":674,"fu":"Update","cl":"Particle Manager","du":174031,"st":113022105,"pC":1348,"cI":0,"cB":1960},{"fr":676,"fu":"Update","cl":"Particle Manager","du":164018,"st":113391917,"pC":1352,"cI":0,"cB":1972},{"fr":678,"fu":"Update","cl":"Particle Manager","du":163496,"st":113763078,"pC":1356,"cI":0,"cB":1984},{"fr":680,"fu":"Update","cl":"Particle Manager","du":167024,"st":114122092,"pC":1360,"cI":0,"cB":1996},{"fr":681,"fu":"Update","cl":"Particle Manager","du":173604,"st":114324674,"pC":1364,"cI":0,"cB":2008},{"fr":683,"fu":"Update","cl":"Particle Manager","du":170575,"st":114701702,"pC":1368,"cI":0,"cB":2020},{"fr":685,"fu":"Update","cl":"Particle Manager","du":168779,"st":115071617,"pC":1372,"cI":0,"cB":2032},{"fr":687,"fu":"Update","cl":"Particle Manager","du":178438,"st":115431911,"pC":1376,"cI":0,"cB":2044},{"fr":689,"fu":"Update","cl":"Particle Manager","du":170629,"st":115814501,"pC":1380,"cI":0,"cB":2056},{"fr":690,"fu":"Update","cl":"Particle Manager","du":191368,"st":116014343,"pC":1384,"cI":0,"cB":2068},{"fr":692,"fu":"Update","cl":"Particle Manager","du":172455,"st":116400801,"pC":1388,"cI":0,"cB":2080},{"fr":694,"fu":"Update","cl":"Particle Manager","du":170630,"st":116770358,"pC":1392,"cI":0,"cB":2092},{"fr":696,"fu":"Update","cl":"Particle Manager","du":180821,"st":117139684,"pC":1396,"cI":0,"cB":2104},{"fr":697,"fu":"Update","cl":"Particle Manager","du":179749,"st":117345143,"pC":1400,"cI":0,"cB":2116},{"fr":699,"fu":"Update","cl":"Particle Manager","du":281141,"st":117730797,"pC":1404,"cI":0,"cB":2128},{"fr":700,"fu":"Update","cl":"Particle Manager","du":174880,"st":118038103,"pC":1408,"cI":0,"cB":2140},{"fr":702,"fu":"Update","cl":"Particle Manager","du":185517,"st":118452649,"pC":1412,"cI":0,"cB":2152},{"fr":703,"fu":"Update","cl":"Particle Manager","du":181258,"st":118664029,"pC":1416,"cI":0,"cB":2164},{"fr":705,"fu":"Update","cl":"Particle Manager","du":180385,"st":119042237,"pC":1420,"cI":0,"cB":2176},{"fr":707,"fu":"Update","cl":"Particle Manager","du":186540,"st":119411774,"pC":1424,"cI":0,"cB":2188},{"fr":709,"fu":"Update","cl":"Particle Manager","du":193411,"st":119792384,"pC":1428,"cI":0,"cB":2200},{"fr":710,"fu":"Update","cl":"Particle Manager","du":179634,"st":120014641,"pC":1432,"cI":0,"cB":2212},{"fr":712,"fu":"Update","cl":"Particle Manager","du":187667,"st":120383102,"pC":1436,"cI":0,"cB":2224},{"fr":714,"fu":"Update","cl":"Particle Manager","du":185420,"st":120763011,"pC":1440,"cI":0,"cB":2236},{"fr":716,"fu":"Update","cl":"Particle Manager","du":185384,"st":121142790,"pC":1444,"cI":0,"cB":2248},{"fr":717,"fu":"Update","cl":"Particle Manager","du":183291,"st":121358026,"pC":1448,"cI":0,"cB":2260},{"fr":719,"fu":"Update","cl":"Particle Manager","du":194422,"st":121733488,"pC":1452,"cI":0,"cB":2272},{"fr":721,"fu":"Update","cl":"Particle Manager","du":200099,"st":122123068,"pC":1456,"cI":0,"cB":2284},{"fr":722,"fu":"Update","cl":"Particle Manager","du":192070,"st":122348470,"pC":1460,"cI":0,"cB":2296},{"fr":724,"fu":"Update","cl":"Particle Manager","du":210393,"st":122741697,"pC":1464,"cI":0,"cB":2308},{"fr":725,"fu":"Update","cl":"Particle Manager","du":190513,"st":122984770,"pC":1468,"cI":0,"cB":2320},{"fr":727,"fu":"Update","cl":"Particle Manager","du":192130,"st":123362194,"pC":1472,"cI":0,"cB":2332},{"fr":729,"fu":"Update","cl":"Particle Manager","du":200253,"st":123752516,"pC":1476,"cI":0,"cB":2344},{"fr":730,"fu":"Update","cl":"Particle Manager","du":193863,"st":123986019,"pC":1480,"cI":0,"cB":2356},{"fr":732,"fu":"Update","cl":"Particle Manager","du":193655,"st":124372480,"pC":1484,"cI":0,"cB":2368},{"fr":734,"fu":"Update","cl":"Particle Manager","du":201643,"st":124766020,"pC":1488,"cI":0,"cB":2380},{"fr":735,"fu":"Update","cl":"Particle Manager","du":195349,"st":125005129,"pC":1492,"cI":0,"cB":2392},{"fr":737,"fu":"Update","cl":"Particle Manager","du":198400,"st":125392217,"pC":1496,"cI":0,"cB":2404},{"fr":739,"fu":"Update","cl":"Particle Manager","du":214187,"st":125781981,"pC":1500,"cI":0,"cB":2416},{"fr":740,"fu":"Update","cl":"Particle Manager","du":202755,"st":126027640,"pC":1504,"cI":0,"cB":2428},{"fr":742,"fu":"Update","cl":"Particle Manager","du":202058,"st":126433149,"pC":1508,"cI":0,"cB":2440},{"fr":743,"fu":"Update","cl":"Particle Manager","du":200255,"st":126665354,"pC":1512,"cI":0,"cB":2452},{"fr":745,"fu":"Update","cl":"Particle Manager","du":204446,"st":127052305,"pC":1516,"cI":0,"cB":2464},{"fr":747,"fu":"Update","cl":"Particle Manager","du":210245,"st":127453190,"pC":1520,"cI":0,"cB":2476},{"fr":748,"fu":"Update","cl":"Particle Manager","du":212232,"st":127694722,"pC":1524,"cI":0,"cB":2488},{"fr":750,"fu":"Update","cl":"Particle Manager","du":220397,"st":128102568,"pC":1528,"cI":0,"cB":2500},{"fr":751,"fu":"Update","cl":"Particle Manager","du":216709,"st":128358577,"pC":1532,"cI":0,"cB":2512},{"fr":753,"fu":"Update","cl":"Particle Manager","du":210948,"st":128771805,"pC":1536,"cI":0,"cB":2524},{"fr":754,"fu":"Update","cl":"Particle Manager","du":210895,"st":129006437,"pC":1540,"cI":0,"cB":2536},{"fr":756,"fu":"Update","cl":"Particle Manager","du":213145,"st":129412188,"pC":1544,"cI":0,"cB":2548},{"fr":757,"fu":"Update","cl":"Particle Manager","du":210674,"st":129654002,"pC":1548,"cI":0,"cB":2564},{"fr":759,"fu":"Update","cl":"Particle Manager","du":233748,"st":130052485,"pC":1552,"cI":0,"cB":2580},{"fr":761,"fu":"Update","cl":"Particle Manager","du":213567,"st":130482651,"pC":1556,"cI":0,"cB":2596},{"fr":762,"fu":"Update","cl":"Particle Manager","du":214071,"st":130726919,"pC":1560,"cI":0,"cB":2612},{"fr":764,"fu":"Update","cl":"Particle Manager","du":223221,"st":131131994,"pC":1564,"cI":0,"cB":2628},{"fr":765,"fu":"Update","cl":"Particle Manager","du":220747,"st":131385969,"pC":1568,"cI":0,"cB":2644},{"fr":767,"fu":"Update","cl":"Particle Manager","du":221597,"st":131801984,"pC":1572,"cI":0,"cB":2660},{"fr":768,"fu":"Update","cl":"Particle Manager","du":226493,"st":132048187,"pC":1576,"cI":0,"cB":2676},{"fr":770,"fu":"Update","cl":"Particle Manager","du":220320,"st":132472105,"pC":1580,"cI":0,"cB":2692},{"fr":771,"fu":"Update","cl":"Particle Manager","du":219424,"st":132715632,"pC":1584,"cI":0,"cB":2708},{"fr":773,"fu":"Update","cl":"Particle Manager","du":225761,"st":133132788,"pC":1588,"cI":0,"cB":2724},{"fr":774,"fu":"Update","cl":"Particle Manager","du":227241,"st":133388517,"pC":1592,"cI":0,"cB":2740},{"fr":776,"fu":"Update","cl":"Particle Manager","du":229110,"st":133812788,"pC":1596,"cI":0,"cB":2756},{"fr":777,"fu":"Update","cl":"Particle Manager","du":238017,"st":134068338,"pC":1600,"cI":0,"cB":2772},{"fr":778,"fu":"Update","cl":"Particle Manager","du":235042,"st":134333925,"pC":1604,"cI":0,"cB":2788},{"fr":780,"fu":"Update","cl":"Particle Manager","du":231845,"st":134752823,"pC":1608,"cI":0,"cB":2804},{"fr":781,"fu":"Update","cl":"Particle Manager","du":238932,"st":135017448,"pC":1612,"cI":0,"cB":2820},{"fr":783,"fu":"Update","cl":"Particle Manager","du":231671,"st":135452373,"pC":1616,"cI":0,"cB":2836},{"fr":784,"fu":"Update","cl":"Particle Manager","du":244961,"st":135716131,"pC":1620,"cI":0,"cB":2852},{"fr":785,"fu":"Update","cl":"Particle Manager","du":235328,"st":135984854,"pC":1624,"cI":0,"cB":2868},{"fr":787,"fu":"Update","cl":"Particle Manager","du":237574,"st":136401879,"pC":1628,"cI":0,"cB":2884},{"fr":788,"fu":"Update","cl":"Particle Manager","du":237281,"st":136664803,"pC":1632,"cI":0,"cB":2900},{"fr":790,"fu":"Update","cl":"Particle Manager","du":243183,"st":137092037,"pC":1636,"cI":0,"cB":2916},{"fr":791,"fu":"Update","cl":"Particle Manager","du":256257,"st":137367917,"pC":1640,"cI":0,"cB":2932},{"fr":793,"fu":"Update","cl":"Particle Manager","du":247430,"st":137820449,"pC":1644,"cI":0,"cB":2948},{"fr":794,"fu":"Update","cl":"Particle Manager","du":251788,"st":138098339,"pC":1648,"cI":0,"cB":2964},{"fr":795,"fu":"Update","cl":"Particle Manager","du":262153,"st":138384204,"pC":1652,"cI":0,"cB":2980},{"fr":796,"fu":"Update","cl":"Particle Manager","du":267535,"st":138674349,"pC":1656,"cI":0,"cB":2996},{"fr":798,"fu":"Update","cl":"Particle Manager","du":259777,"st":139149832,"pC":1660,"cI":0,"cB":3012},{"fr":799,"fu":"Update","cl":"Particle Manager","du":249125,"st":139440340,"pC":1664,"cI":0,"cB":3028},{"fr":800,"fu":"Update","cl":"Particle Manager","du":246807,"st":139715564,"pC":1668,"cI":0,"cB":3044},{"fr":801,"fu":"Update","cl":"Particle Manager","du":247031,"st":139986100,"pC":1672,"cI":0,"cB":3060},{"fr":803,"fu":"Update","cl":"Particle Manager","du":281919,"st":140450155,"pC":1676,"cI":0,"cB":3076},{"fr":804,"fu":"Update","cl":"Particle Manager","du":266213,"st":140759081,"pC":1680,"cI":0,"cB":3092},{"fr":805,"fu":"Update","cl":"Particle Manager","du":250144,"st":141055302,"pC":1684,"cI":0,"cB":3108},{"fr":806,"fu":"Update","cl":"Particle Manager","du":254439,"st":141339334,"pC":1688,"cI":0,"cB":3124},{"fr":808,"fu":"Update","cl":"Particle Manager","du":255721,"st":141779467,"pC":1692,"cI":0,"cB":3140},{"fr":809,"fu":"Update","cl":"Particle Manager","du":256838,"st":142065391,"pC":1696,"cI":0,"cB":3156},{"fr":810,"fu":"Update","cl":"Particle Manager","du":273566,"st":142343927,"pC":1700,"cI":0,"cB":3172},{"fr":812,"fu":"Update","cl":"Particle Manager","du":258535,"st":142807635,"pC":1704,"cI":0,"cB":3188},{"fr":813,"fu":"Update","cl":"Particle Manager","du":255554,"st":143094792,"pC":1708,"cI":0,"cB":3204},{"fr":814,"fu":"Update","cl":"Particle Manager","du":269582,"st":143374569,"pC":1712,"cI":0,"cB":3220},{"fr":815,"fu":"Update","cl":"Particle Manager","du":271040,"st":143666775,"pC":1716,"cI":0,"cB":3236},{"fr":817,"fu":"Update","cl":"Particle Manager","du":275183,"st":144133609,"pC":1720,"cI":0,"cB":3252},{"fr":818,"fu":"Update","cl":"Particle Manager","du":269963,"st":144435416,"pC":1724,"cI":0,"cB":3268},{"fr":819,"fu":"Update","cl":"Particle Manager","du":266465,"st":144736704,"pC":1728,"cI":0,"cB":3284},{"fr":820,"fu":"Update","cl":"Particle Manager","du":263678,"st":145026640,"pC":1732,"cI":0,"cB":3300},{"fr":822,"fu":"Update","cl":"Particle Manager","du":267112,"st":145482844,"pC":1736,"cI":0,"cB":3316},{"fr":823,"fu":"Update","cl":"Particle Manager","du":265926,"st":145785642,"pC":1740,"cI":0,"cB":3332},{"fr":824,"fu":"Update","cl":"Particle Manager","du":279010,"st":146073819,"pC":1744,"cI":0,"cB":3348},{"fr":825,"fu":"Update","cl":"Particle Manager","du":278458,"st":146372909,"pC":1748,"cI":0,"cB":3364},{"fr":826,"fu":"Update","cl":"Particle Manager","du":273037,"st":146677667,"pC":1752,"cI":0,"cB":3380},{"fr":828,"fu":"Update","cl":"Particle Manager","du":273197,"st":147141939,"pC":1756,"cI":0,"cB":3396},{"fr":829,"fu":"Update","cl":"Particle Manager","du":271408,"st":147444907,"pC":1760,"cI":0,"cB":3412},{"fr":830,"fu":"Update","cl":"Particle Manager","du":285363,"st":147742879,"pC":1764,"cI":0,"cB":3428},{"fr":831,"fu":"Update","cl":"Particle Manager","du":276486,"st":148058089,"pC":1768,"cI":0,"cB":3444},{"fr":832,"fu":"Update","cl":"Particle Manager","du":313139,"st":148364571,"pC":1772,"cI":0,"cB":3460},{"fr":833,"fu":"Update","cl":"Particle Manager","du":283782,"st":148694853,"pC":1776,"cI":0,"cB":3476},{"fr":834,"fu":"Update","cl":"Particle Manager","du":338259,"st":149004321,"pC":1780,"cI":0,"cB":3492},{"fr":835,"fu":"Update","cl":"Particle Manager","du":282444,"st":149367909,"pC":1784,"cI":0,"cB":3508},{"fr":836,"fu":"Update","cl":"Particle Manager","du":282302,"st":149675609,"pC":1788,"cI":0,"cB":3524},{"fr":837,"fu":"Update","cl":"Particle Manager","du":288338,"st":149987775,"pC":1792,"cI":0,"cB":3540},{"fr":839,"fu":"Update","cl":"Particle Manager","du":292796,"st":150474021,"pC":1796,"cI":0,"cB":3556},{"fr":840,"fu":"Update","cl":"Particle Manager","du":285997,"st":150796091,"pC":1800,"cI":0,"cB":3572},{"fr":841,"fu":"Update","cl":"Particle Manager","du":284096,"st":151104704,"pC":1804,"cI":0,"cB":3588},{"fr":842,"fu":"Update","cl":"Particle Manager","du":297807,"st":151405048,"pC":1808,"cI":0,"cB":3604},{"fr":843,"fu":"Update","cl":"Particle Manager","du":287705,"st":151727451,"pC":1812,"cI":0,"cB":3620},{"fr":844,"fu":"Update","cl":"Particle Manager","du":289217,"st":152046178,"pC":1816,"cI":0,"cB":3636},{"fr":845,"fu":"Update","cl":"Particle Manager","du":310227,"st":152362376,"pC":1820,"cI":0,"cB":3652},{"fr":846,"fu":"Update","cl":"Particle Manager","du":299769,"st":152708577,"pC":1824,"cI":0,"cB":3668},{"fr":847,"fu":"Update","cl":"Particle Manager","du":293070,"st":153036889,"pC":1828,"cI":0,"cB":3684},{"fr":848,"fu":"Update","cl":"Particle Manager","du":294358,"st":153351510,"pC":1832,"cI":0,"cB":3700},{"fr":849,"fu":"Update","cl":"Particle Manager","du":294921,"st":153675462,"pC":1836,"cI":0,"cB":3716},{"fr":850,"fu":"Update","cl":"Particle Manager","du":299183,"st":153994297,"pC":1840,"cI":0,"cB":3732},{"fr":852,"fu":"Update","cl":"Particle Manager","du":309519,"st":154478130,"pC":1844,"cI":0,"cB":3748},{"fr":853,"fu":"Update","cl":"Particle Manager","du":306255,"st":154814593,"pC":1848,"cI":0,"cB":3764},{"fr":854,"fu":"Update","cl":"Particle Manager","du":301063,"st":155143916,"pC":1852,"cI":0,"cB":3780},{"fr":855,"fu":"Update","cl":"Particle Manager","du":327350,"st":155473577,"pC":1856,"cI":0,"cB":3796},{"fr":856,"fu":"Update","cl":"Particle Manager","du":323633,"st":155824837,"pC":1860,"cI":0,"cB":3812},{"fr":857,"fu":"Update","cl":"Particle Manager","du":314538,"st":156174372,"pC":1864,"cI":0,"cB":3828},{"fr":858,"fu":"Update","cl":"Particle Manager","du":0,"st":156511982,"pC":1868,"cI":0,"cB":3844}]}